ruby_commit_helper/__main__.py
ruby_commit_helper/main.py
ruby_commit_helper-2025.4.3.1.dist-info/METADATA
ruby_commit_helper-2025.4.3.1.dist-info/WHEEL
ruby_commit_helper-2025.4.3.1.dist-info/entry_points.txt
ruby_commit_helper-2025.4.3.1.dist-info/licenses/LICENSE
ruby_commit_helper-2025.4.3.1.dist-info/RECORD
