Metadata-Version: 2.4
Name: ruby-commit-helper
Version: 2025.4.3.1
Summary: No more "offend" for your ruby commit!
License-File: LICENSE
Requires-Python: >=3.10
Requires-Dist: rich>=13.9.4
